Broaden_Spectrum.py
GUI_GO.py
KK_And_Merge.py
Thesis-plots.py
Ti34_XAS_Python.py
data_structure.py
data_viewer.py
global_optimization.py
main.py
material_model.py
material_structure.py
setup_reflectivity.py
GO_RXR-0.3.dist-info/METADATA
GO_RXR-0.3.dist-info/WHEEL
GO_RXR-0.3.dist-info/license.txt
GO_RXR-0.3.dist-info/top_level.txt
GO_RXR-0.3.dist-info/RECORD
